pyeal/__init__.py
pyeal/__main__.py
pyeal/_command.py
pyeal/cli.py
pyeal/exc.py
pyeal/module_data.py
pyeal/res.py
pyeal/seal.py
pyeal/assets/icon.ico
pyeal/assets/mel_template_lib.mel
pyeal/codekit/__init__.py
pyeal/codekit/core.py
pyeal/codekit/unparse.py
pyeal-1.0.6.dist-info/LICENSE
pyeal-1.0.6.dist-info/METADATA
pyeal-1.0.6.dist-info/WHEEL
pyeal-1.0.6.dist-info/entry_points.txt
pyeal-1.0.6.dist-info/top_level.txt
pyeal-1.0.6.dist-info/RECORD
